[
    
  {
    "id": 1766219426026,
    "name": "상자",
    "type": "상자",
    "y": 987,
    "x": 967,
    "desc": "",
    "link": "",
    "image": ""
  },
  {
    "id": 1766219411906,
    "name": "상자",
    "type": "상자",
    "y": 1122,
    "x": 946,
    "desc": "",
    "link": "",
    "image": ""
  },
  {
    "id": 1766219396618,
    "name": "상자",
    "type": "상자",
    "y": 920,
    "x": 1110,
    "desc": "",
    "link": "",
    "image": ""
  },
  {
    "id": 1766219262210,
    "name": "도난당한 개연주",
    "type": "기연",
    "y": 838,
    "x": 1288,
    "desc": "불탄 이후 진행 지점, 바로 위 원숭이들이 가지고 있음",
    "link": "",
    "image": ""
  },
  {
    "id": 1766219169483,
    "name": "꿈의 불선선",
    "type": "경계석",
    "y": 1156,
    "x": 1728,
    "desc": "",
    "link": "",
    "image": ""
  }
]